lcdp_sqlalchemy_utils/__init__.py
lcdp_sqlalchemy_utils/env.py
lcdp_sqlalchemy_utils/env_async.py
lcdp_sqlalchemy_utils/exceptions/InvalidOrderByException.py
lcdp_sqlalchemy_utils/exceptions/__init__.py
lcdp_sqlalchemy_utils/migrate.py
lcdp_sqlalchemy_utils/order_by_mapper.py
lcdp_sqlalchemy_utils/postgres.py
lcdp_sqlalchemy_utils/query_executor.py
lcdp_sqlalchemy_utils-1.5.9.dist-info/METADATA
lcdp_sqlalchemy_utils-1.5.9.dist-info/WHEEL
lcdp_sqlalchemy_utils-1.5.9.dist-info/RECORD
