Metadata-Version: 2.4
Name: lcdp-sqlalchemy-utils
Version: 1.5.9
Summary: SQLAlchemy Utils
Author: Le Comptoir Des Pharmacies
Author-email: webmaster@lecomptoirdespharmacies.fr
Requires-Python: >=3.8
Classifier: Programming Language :: Python :: 3
Classifier: Programming Language :: Python :: 3.8
Classifier: Programming Language :: Python :: 3.9
Classifier: Programming Language :: Python :: 3.10
Classifier: Programming Language :: Python :: 3.11
Classifier: Programming Language :: Python :: 3.12
Classifier: Programming Language :: Python :: 3.13
Classifier: Programming Language :: Python :: 3.14
Requires-Dist: SQLAlchemy (==2.0.40)
Requires-Dist: alembic (==1.8.1)
Requires-Dist: dataclasses-json (==0.5.7)
Requires-Dist: nest_asyncio (==1.5.8)
